{
  "desktop": {
    "audioLightboxDescriptionFontSize": 18,
    "audioToggleScale": 0.6,
    "audioToggleSize": 84,
    "bgStarCount": 950,
    "bgStarMaxBrightness": 0.45,
    "bgStarMinBrightness": 0.25,
    "bgStarSizeRandomness": 10,
    "bgStarTwinkleAmount": 100,
    "bgStarTwinkleSpeed": 2.7,
    "bgStarTwinkleSpeedRandomness": 100,
    "bgYPosition": 0,
    "blurIntensity": 50,
    "blurIntensity2": 50,
    "descriptionFontSize": 15,
    "descriptionVerticalPosition": 10,
    "descriptionXOffset": 0,
    "descriptionYOffset": -130,
    "joinBetaFontSize": 30,
    "joinBetaHorizontalOffset": 0,
    "joinBetaVerticalOffset": -170,
    "lineLength2": 2.4,
    "lineLength3": 5,
    "logoSize": 500,
    "logoYPosition": 0,
    "motionBlurEnabled": true,
    "motionBlurEnabled2": false,
    "phaseBlurAmount": 0,
    "phaseBlurAmountSelected": 14,
    "phaseColumnHeight": 600,
    "phaseColumnYOffset": -150,
    "phaseDescriptionFontSize": 12,
    "phaseFadePosition": 60,
    "phaseHeaderFontSize": 35,
    "phaseHoverDarkeningIntensity": 90,
    "phaseIdleBackdropBlur": 8,
    "phaseImageDarkening": 0,
    "phaseImageIdleOpacity": 100,
    "powerButtonHorizontalOffset": 21,
    "powerButtonScale": 0.65,
    "powerButtonVerticalOffset": -20,
    "proceedButtonSize": 1,
    "proceedButtonVerticalPosition": -55,
    "sizeRandomness": 5,
    "sizeRandomness2": 50,
    "sizeRandomness3": 50,
    "soundLabelHorizontalOffset": 0,
    "soundLabelSize": 16,
    "soundLabelVerticalOffset": 0,
    "spawnDelay3": 470,
    "starFadeFeatherSize": 480,
    "starFadePosition": 23,
    "starFrequency": 540,
    "starFrequency2": 105,
    "starFrequency3": 1,
    "starScale": 0.3,
    "starScale2": 0.3,
    "starScale3": 0.9,
    "starSpeed": 1.5,
    "starSpeed2": 10,
    "starSpeed3": 125,
    "toggleGroupVerticalPosition": -10,
    "toggleTextGap": 4,
    "twinkleAmount": 35,
    "twinkleAmount2": 30,
    "twinkleAmount3": 0,
    "twinkleSpeed": 5,
    "twinkleSpeed2": 5,
    "twinkleSpeed3": 1,
    "twinkleSpeedRandomness": 55,
    "twinkleSpeedRandomness2": 60,
    "twinkleSpeedRandomness3": 50
  },
  "shared": {
    "selectedFont": "Saira",
    "descriptionText": "An epic idle strategy game where Mekanism NFTs build empires.\nComing soon.",
    "descriptionColor": "text-gray-400",
    "designVariation": "modern",
    "phaseHeaderFont": "Rajdhani",
    "phaseHeaderColor": "text-white/70",
    "phaseDescriptionFont": "Saira",
    "soundLabelFont": "Orbitron",
    "soundLabelColor": "text-yellow-400/90",
    "powerButtonGlowEnabled": true,
    "speakerIconStyle": "geometric",
    "phaseImage1": "",
    "phaseImage2": "",
    "phaseImage3": "",
    "phaseImage4": "",
    "phaseImageBlendMode": "normal",
    "descriptionCardBlur": 40,
    "descriptionCardDarkness": 40,
    "descriptionCardBorder": true,
    "logoFadeDuration": 1000,
    "lightboxBackdropDarkness": 10,
    "joinBetaFont": "Rajdhani",
    "joinBetaColor": "text-white",
    "audioLightboxDescriptionFont": "Arial",
    "audioLightboxDescriptionColor": "text-white/70"
  }
}
